codeassistant/__init__.py
codeassistant/click_args.py
codeassistant/click_kwargs.py
codeassistant/functions_cmds.py
codeassistant/functions_core.py
codeassistant/functions_git.py
codeassistant/main.py
codeassistant/variables.py
CodeAss-0.17.2.dist-info/METADATA
CodeAss-0.17.2.dist-info/WHEEL
CodeAss-0.17.2.dist-info/entry_points.txt
CodeAss-0.17.2.dist-info/top_level.txt
CodeAss-0.17.2.dist-info/RECORD
