Metadata-Version: 2.1
Name: CodeAss
Version: 0.17.2
Summary: Code Assistant
Author: HullaBulla
Author-email: hullabulla666@gmail.com
Classifier: Programming Language :: Python :: 3.11
Classifier: Programming Language :: Python :: 3.10
Requires-Python: >=3.10
Requires-Dist: click>=7.1.2
Requires-Dist: virtualenv
Requires-Dist: rich
Requires-Dist: typeguard
Requires-Dist: pytest
Requires-Dist: shell-gpt
Requires-Dist: tqdm
Requires-Dist: twine
Requires-Dist: build
Requires-Dist: pathspec
Requires-Dist: mypy
